[{"hs6":"710110","statisticalCode":"000","code":"710110000","description":"Natural pearls","general":{"text":"Free","percent":0},"temporary":{"text":"","percent":null},"wto":{"text":"Free","percent":0},"chinaRcep":{"text":"Free","percent":0}},{"hs6":"710110","statisticalCode":"","code":"710110","description":"Cultured pearls :","general":{"text":"Free","percent":0},"temporary":{"text":"","percent":null},"wto":{"text":"Free","percent":0},"chinaRcep":{"text":"Free","percent":0}},{"hs6":"710121","statisticalCode":"","code":"710121","description":"Unworked","general":{"text":"Free","percent":0},"temporary":{"text":"","percent":null},"wto":{"text":"Free","percent":0},"chinaRcep":{"text":"","percent":null}},{"hs6":"710121","statisticalCode":"110","code":"710121110","description":"- Akoya pearls","general":{"text":"Free","percent":0},"temporary":{"text":"","percent":null},"wto":{"text":"Free","percent":0},"chinaRcep":{"text":"Free","percent":0}},{"hs6":"710121","statisticalCode":"120","code":"710121120","description":"- Silver lipped pearls and Black lipped pearls","general":{"text":"Free","percent":0},"temporary":{"text":"","percent":null},"wto":{"text":"Free","percent":0},"chinaRcep":{"text":"Free","percent":0}},{"hs6":"710121","statisticalCode":"190","code":"710121190","description":"- Other","general":{"text":"Free","percent":0},"temporary":{"text":"","percent":null},"wto":{"text":"Free","percent":0},"chinaRcep":{"text":"Free","percent":0}},{"hs6":"710122","statisticalCode":"","code":"710122","description":"Worked","general":{"text":"Free","percent":0},"temporary":{"text":"","percent":null},"wto":{"text":"Free","percent":0},"chinaRcep":{"text":"","percent":null}},{"hs6":"710122","statisticalCode":"210","code":"710122210","description":"- Akoya pearls","general":{"text":"Free","percent":0},"temporary":{"text":"","percent":null},"wto":{"text":"Free","percent":0},"chinaRcep":{"text":"Free","percent":0}},{"hs6":"710122","statisticalCode":"220","code":"710122220","description":"- Silver lipped pearls and Black lipped pearls","general":{"text":"Free","percent":0},"temporary":{"text":"","percent":null},"wto":{"text":"Free","percent":0},"chinaRcep":{"text":"Free","percent":0}},{"hs6":"710122","statisticalCode":"290","code":"710122290","description":"- Other","general":{"text":"Free","percent":0},"temporary":{"text":"","percent":null},"wto":{"text":"Free","percent":0},"chinaRcep":{"text":"Free","percent":0}},{"hs6":"710122","statisticalCode":"","code":"710122","description":"Diamonds, whether or not worked, but not mounted or set","general":{"text":"Free","percent":0},"temporary":{"text":"","percent":null},"wto":{"text":"Free","percent":0},"chinaRcep":{"text":"","percent":null}},{"hs6":"710210","statisticalCode":"000","code":"710210000","description":"Unsorted","general":{"text":"Free","percent":0},"temporary":{"text":"","percent":null},"wto":{"text":"Free","percent":0},"chinaRcep":{"text":"Free","percent":0}},{"hs6":"710210","statisticalCode":"","code":"710210","description":"Industrial :","general":{"text":"Free","percent":0},"temporary":{"text":"","percent":null},"wto":{"text":"Free","percent":0},"chinaRcep":{"text":"Free","percent":0}},{"hs6":"710221","statisticalCode":"000","code":"710221000","description":"Unworked or simply sawn, cleaved or bruted","general":{"text":"Free","percent":0},"temporary":{"text":"","percent":null},"wto":{"text":"Free","percent":0},"chinaRcep":{"text":"Free","percent":0}},{"hs6":"710229","statisticalCode":"000","code":"710229000","description":"Other","general":{"text":"Free","percent":0},"temporary":{"text":"","percent":null},"wto":{"text":"Free","percent":0},"chinaRcep":{"text":"Free","percent":0}},{"hs6":"710229","statisticalCode":"","code":"710229","description":"Non-industrial :","general":{"text":"Free","percent":0},"temporary":{"text":"","percent":null},"wto":{"text":"Free","percent":0},"chinaRcep":{"text":"Free","percent":0}},{"hs6":"710231","statisticalCode":"000","code":"710231000","description":"Unworked or simply sawn, cleaved or bruted","general":{"text":"Free","percent":0},"temporary":{"text":"","percent":null},"wto":{"text":"Free","percent":0},"chinaRcep":{"text":"Free","percent":0}},{"hs6":"710239","statisticalCode":"000","code":"710239000","description":"Other","general":{"text":"Free","percent":0},"temporary":{"text":"","percent":null},"wto":{"text":"Free","percent":0},"chinaRcep":{"text":"Free","percent":0}},{"hs6":"710239","statisticalCode":"","code":"710239","description":"Precious stones (other than diamonds) and semi-precious stones, whether or not worked or graded but not strung, mounted or set; ungraded precious stones (other than diamonds) and semi-precious stones, temporarily strung for convenience of transport","general":{"text":"Free","percent":0},"temporary":{"text":"","percent":null},"wto":{"text":"Free","percent":0},"chinaRcep":{"text":"Free","percent":0}},{"hs6":"710310","statisticalCode":"000","code":"710310000","description":"Unworked or simply sawn or roughly shaped","general":{"text":"Free","percent":0},"temporary":{"text":"","percent":null},"wto":{"text":"Free","percent":0},"chinaRcep":{"text":"Free","percent":0}},{"hs6":"710310","statisticalCode":"","code":"710310","description":"Otherwise worked :","general":{"text":"Free","percent":0},"temporary":{"text":"","percent":null},"wto":{"text":"Free","percent":0},"chinaRcep":{"text":"Free","percent":0}},{"hs6":"710391","statisticalCode":"000","code":"710391000","description":"Rubies, sapphires and emeralds","general":{"text":"Free","percent":0},"temporary":{"text":"","percent":null},"wto":{"text":"Free","percent":0},"chinaRcep":{"text":"Free","percent":0}},{"hs6":"710399","statisticalCode":"000","code":"710399000","description":"Other","general":{"text":"Free","percent":0},"temporary":{"text":"","percent":null},"wto":{"text":"Free","percent":0},"chinaRcep":{"text":"Free","percent":0}},{"hs6":"710399","statisticalCode":"","code":"710399","description":"Synthetic or reconstructed precious or semi-precious stones, whether or not worked or graded but not strung, mounted or set; ungraded synthetic or reconstructed precious or semi-precious stones, temporarily strung for convenience of transport","general":{"text":"Free","percent":0},"temporary":{"text":"","percent":null},"wto":{"text":"Free","percent":0},"chinaRcep":{"text":"Free","percent":0}},{"hs6":"710410","statisticalCode":"000","code":"710410000","description":"Piezo-electric quartz","general":{"text":"Free","percent":0},"temporary":{"text":"","percent":null},"wto":{"text":"Free","percent":0},"chinaRcep":{"text":"Free","percent":0}},{"hs6":"710410","statisticalCode":"","code":"710410","description":"Other, unworked or simply sawn or roughly shaped :","general":{"text":"Free","percent":0},"temporary":{"text":"","percent":null},"wto":{"text":"Free","percent":0},"chinaRcep":{"text":"Free","percent":0}},{"hs6":"710421","statisticalCode":"000","code":"710421000","description":"Diamonds","general":{"text":"Free","percent":0},"temporary":{"text":"","percent":null},"wto":{"text":"Free","percent":0},"chinaRcep":{"text":"Free","percent":0}},{"hs6":"710429","statisticalCode":"000","code":"710429000","description":"Other","general":{"text":"Free","percent":0},"temporary":{"text":"","percent":null},"wto":{"text":"Free","percent":0},"chinaRcep":{"text":"Free","percent":0}},{"hs6":"710429","statisticalCode":"","code":"710429","description":"Other :","general":{"text":"Free","percent":0},"temporary":{"text":"","percent":null},"wto":{"text":"Free","percent":0},"chinaRcep":{"text":"Free","percent":0}},{"hs6":"710491","statisticalCode":"000","code":"710491000","description":"Diamonds","general":{"text":"Free","percent":0},"temporary":{"text":"","percent":null},"wto":{"text":"Free","percent":0},"chinaRcep":{"text":"Free","percent":0}},{"hs6":"710499","statisticalCode":"000","code":"710499000","description":"Other","general":{"text":"Free","percent":0},"temporary":{"text":"","percent":null},"wto":{"text":"Free","percent":0},"chinaRcep":{"text":"Free","percent":0}},{"hs6":"710499","statisticalCode":"","code":"710499","description":"Dust and powder of natural or synthetic precious or semi-precious stones","general":{"text":"Free","percent":0},"temporary":{"text":"","percent":null},"wto":{"text":"Free","percent":0},"chinaRcep":{"text":"Free","percent":0}},{"hs6":"710510","statisticalCode":"000","code":"710510000","description":"Of diamonds","general":{"text":"Free","percent":0},"temporary":{"text":"","percent":null},"wto":{"text":"Free","percent":0},"chinaRcep":{"text":"Free","percent":0}},{"hs6":"710590","statisticalCode":"000","code":"710590000","description":"Other","general":{"text":"Free","percent":0},"temporary":{"text":"","percent":null},"wto":{"text":"Free","percent":0},"chinaRcep":{"text":"Free","percent":0}},{"hs6":"710590","statisticalCode":"","code":"710590","description":"II.- PRECIOUS METALS AND METALS CLAD WITH PRECIOUS METAL","general":{"text":"Free","percent":0},"temporary":{"text":"","percent":null},"wto":{"text":"Free","percent":0},"chinaRcep":{"text":"Free","percent":0}},{"hs6":"710590","statisticalCode":"","code":"710590","description":"Silver (including silver plated with gold or platinum), unwrought or in semi-manufactured forms, or in powder form","general":{"text":"Free","percent":0},"temporary":{"text":"","percent":null},"wto":{"text":"Free","percent":0},"chinaRcep":{"text":"Free","percent":0}},{"hs6":"710610","statisticalCode":"000","code":"710610000","description":"Powder","general":{"text":"Free","percent":0},"temporary":{"text":"","percent":null},"wto":{"text":"Free","percent":0},"chinaRcep":{"text":"Free","percent":0}},{"hs6":"710610","statisticalCode":"","code":"710610","description":"Other :","general":{"text":"Free","percent":0},"temporary":{"text":"","percent":null},"wto":{"text":"Free","percent":0},"chinaRcep":{"text":"Free","percent":0}},{"hs6":"710691","statisticalCode":"000","code":"710691000","description":"Unwrought","general":{"text":"Free","percent":0},"temporary":{"text":"","percent":null},"wto":{"text":"Free","percent":0},"chinaRcep":{"text":"Free","percent":0}},{"hs6":"710692","statisticalCode":"","code":"710692","description":"Semi-manufactured","general":{"text":"Free","percent":0},"temporary":{"text":"","percent":null},"wto":{"text":"","percent":null},"chinaRcep":{"text":"","percent":null}},{"hs6":"710692","statisticalCode":"","code":"710692","description":"- Bars, rods, profiles, plates, sheets and strip","general":{"text":"Free","percent":0},"temporary":{"text":"","percent":null},"wto":{"text":"","percent":null},"chinaRcep":{"text":"","percent":null}},{"hs6":"710692","statisticalCode":"110","code":"710692110","description":"-- Alloyed","general":{"text":"Free","percent":0},"temporary":{"text":"","percent":null},"wto":{"text":"Free","percent":0},"chinaRcep":{"text":"Free","percent":0}},{"hs6":"710692","statisticalCode":"190","code":"710692190","description":"-- Other","general":{"text":"Free","percent":0},"temporary":{"text":"","percent":null},"wto":{"text":"Free","percent":0},"chinaRcep":{"text":"Free","percent":0}},{"hs6":"710692","statisticalCode":"200","code":"710692200","description":"- Other","general":{"text":"Free","percent":0},"temporary":{"text":"","percent":null},"wto":{"text":"Free","percent":0},"chinaRcep":{"text":"Free","percent":0}},{"hs6":"710692","statisticalCode":"","code":"710692","description":"","general":{"text":"Free","percent":0},"temporary":{"text":"","percent":null},"wto":{"text":"","percent":null},"chinaRcep":{"text":"","percent":null}},{"hs6":"710700","statisticalCode":"000","code":"710700000","description":"Base metals clad with silver, not further worked than semi-manufactured","general":{"text":"Free","percent":0},"temporary":{"text":"","percent":null},"wto":{"text":"Free","percent":0},"chinaRcep":{"text":"Free","percent":0}},{"hs6":"710700","statisticalCode":"","code":"710700","description":"Gold (including gold plated with platinum) unwrought or in semi-manufactured forms, or in powder form","general":{"text":"Free","percent":0},"temporary":{"text":"","percent":null},"wto":{"text":"Free","percent":0},"chinaRcep":{"text":"Free","percent":0}},{"hs6":"710700","statisticalCode":"","code":"710700","description":"Non-monetary :","general":{"text":"Free","percent":0},"temporary":{"text":"","percent":null},"wto":{"text":"Free","percent":0},"chinaRcep":{"text":"Free","percent":0}},{"hs6":"710811","statisticalCode":"000","code":"710811000","description":"Powder","general":{"text":"Free","percent":0},"temporary":{"text":"","percent":null},"wto":{"text":"Free","percent":0},"chinaRcep":{"text":"Free","percent":0}},{"hs6":"710812","statisticalCode":"","code":"710812","description":"Other unwrought forms","general":{"text":"Free","percent":0},"temporary":{"text":"","percent":null},"wto":{"text":"Free","percent":0},"chinaRcep":{"text":"","percent":null}},{"hs6":"710812","statisticalCode":"010","code":"710812010","description":"- Engraved with the mark of melter, serial number, purity and weight","general":{"text":"Free","percent":0},"temporary":{"text":"","percent":null},"wto":{"text":"Free","percent":0},"chinaRcep":{"text":"Free","percent":0}},{"hs6":"710812","statisticalCode":"090","code":"710812090","description":"- Other","general":{"text":"Free","percent":0},"temporary":{"text":"","percent":null},"wto":{"text":"Free","percent":0},"chinaRcep":{"text":"Free","percent":0}},{"hs6":"710813","statisticalCode":"","code":"710813","description":"Other semi-manufactured forms","general":{"text":"Free","percent":0},"temporary":{"text":"","percent":null},"wto":{"text":"Free","percent":0},"chinaRcep":{"text":"","percent":null}},{"hs6":"710813","statisticalCode":"010","code":"710813010","description":"- Bars, rods, profiles, plates, sheets and strip","general":{"text":"Free","percent":0},"temporary":{"text":"","percent":null},"wto":{"text":"Free","percent":0},"chinaRcep":{"text":"Free","percent":0}},{"hs6":"710813","statisticalCode":"090","code":"710813090","description":"- Other","general":{"text":"Free","percent":0},"temporary":{"text":"","percent":null},"wto":{"text":"Free","percent":0},"chinaRcep":{"text":"Free","percent":0}},{"hs6":"710820","statisticalCode":"000","code":"710820000","description":"Monetary","general":{"text":"Free","percent":0},"temporary":{"text":"","percent":null},"wto":{"text":"Free","percent":0},"chinaRcep":{"text":"Free","percent":0}},{"hs6":"710820","statisticalCode":"","code":"710820","description":"","general":{"text":"Free","percent":0},"temporary":{"text":"","percent":null},"wto":{"text":"Free","percent":0},"chinaRcep":{"text":"Free","percent":0}},{"hs6":"710900","statisticalCode":"000","code":"710900000","description":"Base metals or silver, clad with gold, not further worked than semi-manufactured","general":{"text":"Free","percent":0},"temporary":{"text":"","percent":null},"wto":{"text":"Free","percent":0},"chinaRcep":{"text":"Free","percent":0}},{"hs6":"710900","statisticalCode":"","code":"710900","description":"Platinum, unwrought or in semi-manufactured forms, or in powder form","general":{"text":"Free","percent":0},"temporary":{"text":"","percent":null},"wto":{"text":"Free","percent":0},"chinaRcep":{"text":"Free","percent":0}},{"hs6":"710900","statisticalCode":"","code":"710900","description":"Platinum :","general":{"text":"Free","percent":0},"temporary":{"text":"","percent":null},"wto":{"text":"Free","percent":0},"chinaRcep":{"text":"Free","percent":0}},{"hs6":"711011","statisticalCode":"000","code":"711011000","description":"Unwrought or in powder form","general":{"text":"Free","percent":0},"temporary":{"text":"","percent":null},"wto":{"text":"Free","percent":0},"chinaRcep":{"text":"Free","percent":0}},{"hs6":"711019","statisticalCode":"","code":"711019","description":"Other","general":{"text":"Free","percent":0},"temporary":{"text":"","percent":null},"wto":{"text":"","percent":null},"chinaRcep":{"text":"","percent":null}},{"hs6":"711019","statisticalCode":"","code":"711019","description":"- Bars, rods, profiles, plates, sheets and strip","general":{"text":"Free","percent":0},"temporary":{"text":"","percent":null},"wto":{"text":"Free","percent":0},"chinaRcep":{"text":"","percent":null}},{"hs6":"711019","statisticalCode":"110","code":"711019110","description":"-- Alloyed","general":{"text":"Free","percent":0},"temporary":{"text":"","percent":null},"wto":{"text":"","percent":null},"chinaRcep":{"text":"Free","percent":0}},{"hs6":"711019","statisticalCode":"190","code":"711019190","description":"-- Other","general":{"text":"Free","percent":0},"temporary":{"text":"","percent":null},"wto":{"text":"","percent":null},"chinaRcep":{"text":"Free","percent":0}},{"hs6":"711019","statisticalCode":"200","code":"711019200","description":"- Other","general":{"text":"Free","percent":0},"temporary":{"text":"","percent":null},"wto":{"text":"Free","percent":0},"chinaRcep":{"text":"Free","percent":0}},{"hs6":"711019","statisticalCode":"","code":"711019","description":"Palladium :","general":{"text":"Free","percent":0},"temporary":{"text":"","percent":null},"wto":{"text":"","percent":null},"chinaRcep":{"text":"","percent":null}},{"hs6":"711021","statisticalCode":"000","code":"711021000","description":"Unwrought or in powder form","general":{"text":"Free","percent":0},"temporary":{"text":"","percent":null},"wto":{"text":"Free","percent":0},"chinaRcep":{"text":"Free","percent":0}},{"hs6":"711029","statisticalCode":"000","code":"711029000","description":"Other","general":{"text":"Free","percent":0},"temporary":{"text":"","percent":null},"wto":{"text":"Free","percent":0},"chinaRcep":{"text":"Free","percent":0}},{"hs6":"711029","statisticalCode":"","code":"711029","description":"Rhodium :","general":{"text":"Free","percent":0},"temporary":{"text":"","percent":null},"wto":{"text":"Free","percent":0},"chinaRcep":{"text":"Free","percent":0}},{"hs6":"711031","statisticalCode":"","code":"711031","description":"Unwrought or in powder form","general":{"text":"Free","percent":0},"temporary":{"text":"","percent":null},"wto":{"text":"Free","percent":0},"chinaRcep":{"text":"","percent":null}},{"hs6":"711031","statisticalCode":"010","code":"711031010","description":"- Powder","general":{"text":"Free","percent":0},"temporary":{"text":"","percent":null},"wto":{"text":"Free","percent":0},"chinaRcep":{"text":"Free","percent":0}},{"hs6":"711031","statisticalCode":"090","code":"711031090","description":"- Other","general":{"text":"Free","percent":0},"temporary":{"text":"","percent":null},"wto":{"text":"Free","percent":0},"chinaRcep":{"text":"Free","percent":0}},{"hs6":"711039","statisticalCode":"000","code":"711039000","description":"Other","general":{"text":"Free","percent":0},"temporary":{"text":"","percent":null},"wto":{"text":"Free","percent":0},"chinaRcep":{"text":"Free","percent":0}},{"hs6":"711039","statisticalCode":"","code":"711039","description":"Iridium, osmium and ruthenium :","general":{"text":"Free","percent":0},"temporary":{"text":"","percent":null},"wto":{"text":"Free","percent":0},"chinaRcep":{"text":"Free","percent":0}},{"hs6":"711041","statisticalCode":"000","code":"711041000","description":"Unwrought or in powder form","general":{"text":"Free","percent":0},"temporary":{"text":"","percent":null},"wto":{"text":"Free","percent":0},"chinaRcep":{"text":"Free","percent":0}},{"hs6":"711049","statisticalCode":"000","code":"711049000","description":"Other","general":{"text":"Free","percent":0},"temporary":{"text":"","percent":null},"wto":{"text":"Free","percent":0},"chinaRcep":{"text":"Free","percent":0}},{"hs6":"711049","statisticalCode":"","code":"711049","description":"","general":{"text":"Free","percent":0},"temporary":{"text":"","percent":null},"wto":{"text":"Free","percent":0},"chinaRcep":{"text":"Free","percent":0}},{"hs6":"711100","statisticalCode":"000","code":"711100000","description":"Base metals, silver or gold, clad with platinum, not further worked than semi-manufactured","general":{"text":"Free","percent":0},"temporary":{"text":"","percent":null},"wto":{"text":"Free","percent":0},"chinaRcep":{"text":"Free","percent":0}},{"hs6":"711100","statisticalCode":"","code":"711100","description":"Waste and scrap of precious metal or of metal clad with precious metal; other waste and scrap containing precious metal or precious metal compounds, of a kind used principally for the recovery of precious metal other than goods of heading 85.49.","general":{"text":"Free","percent":0},"temporary":{"text":"","percent":null},"wto":{"text":"Free","percent":0},"chinaRcep":{"text":"Free","percent":0}},{"hs6":"711230","statisticalCode":"000","code":"711230000","description":"Ash containing precious metal or precious metal compounds","general":{"text":"Free","percent":0},"temporary":{"text":"","percent":null},"wto":{"text":"Free","percent":0},"chinaRcep":{"text":"Free","percent":0}},{"hs6":"711230","statisticalCode":"","code":"711230","description":"Other :","general":{"text":"Free","percent":0},"temporary":{"text":"","percent":null},"wto":{"text":"Free","percent":0},"chinaRcep":{"text":"Free","percent":0}},{"hs6":"711291","statisticalCode":"000","code":"711291000","description":"Of gold, including metal clad with gold but excluding sweepings containing other precious metals","general":{"text":"Free","percent":0},"temporary":{"text":"","percent":null},"wto":{"text":"Free","percent":0},"chinaRcep":{"text":"Free","percent":0}},{"hs6":"711292","statisticalCode":"000","code":"711292000","description":"Of platinum, including metal clad with platinum but excluding sweepings containing other precious metals","general":{"text":"Free","percent":0},"temporary":{"text":"","percent":null},"wto":{"text":"Free","percent":0},"chinaRcep":{"text":"Free","percent":0}},{"hs6":"711299","statisticalCode":"000","code":"711299000","description":"Other","general":{"text":"Free","percent":0},"temporary":{"text":"","percent":null},"wto":{"text":"Free","percent":0},"chinaRcep":{"text":"Free","percent":0}},{"hs6":"711299","statisticalCode":"","code":"711299","description":"III.- JEWELLERY, GOLDSMITHS' AND SILVERSMITHS' WARES AND OTHER ARTICLES","general":{"text":"Free","percent":0},"temporary":{"text":"","percent":null},"wto":{"text":"Free","percent":0},"chinaRcep":{"text":"Free","percent":0}},{"hs6":"711299","statisticalCode":"","code":"711299","description":"Articles of jewellery and parts thereof, of precious metal or of metal clad with precious metal","general":{"text":"Free","percent":0},"temporary":{"text":"","percent":null},"wto":{"text":"Free","percent":0},"chinaRcep":{"text":"Free","percent":0}},{"hs6":"711299","statisticalCode":"","code":"711299","description":"Of precious metal whether or not plated or clad with precious metal :","general":{"text":"Free","percent":0},"temporary":{"text":"","percent":null},"wto":{"text":"Free","percent":0},"chinaRcep":{"text":"Free","percent":0}},{"hs6":"711311","statisticalCode":"000","code":"711311000","description":"Of silver, whether or not plated or clad with other precious metal","general":{"text":"6.2%","percent":6.2},"temporary":{"text":"","percent":null},"wto":{"text":"5.2%","percent":5.2},"chinaRcep":{"text":"2.4%","percent":2.4}},{"hs6":"711319","statisticalCode":"","code":"711319","description":"Of other precious metal, whether or not plated or clad with precious metal","general":{"text":"","percent":null},"temporary":{"text":"","percent":null},"wto":{"text":"","percent":null},"chinaRcep":{"text":"","percent":null}},{"hs6":"711319","statisticalCode":"010","code":"711319010","description":"1 Of platinum, whether or not plated or clad with other precious metal","general":{"text":"6.2%","percent":6.2},"temporary":{"text":"","percent":null},"wto":{"text":"5.2%","percent":5.2},"chinaRcep":{"text":"2.4%","percent":2.4}},{"hs6":"711319","statisticalCode":"","code":"711319","description":"2 Other","general":{"text":"6.6%","percent":6.6},"temporary":{"text":"","percent":null},"wto":{"text":"5.4%","percent":5.4},"chinaRcep":{"text":"","percent":null}},{"hs6":"711319","statisticalCode":"021","code":"711319021","description":"- Chains for watches, spectacles or pince-nez and other ornamental chains worn on person","general":{"text":"","percent":null},"temporary":{"text":"","percent":null},"wto":{"text":"","percent":null},"chinaRcep":{"text":"2.5%","percent":2.5}},{"hs6":"711319","statisticalCode":"029","code":"711319029","description":"- Other","general":{"text":"","percent":null},"temporary":{"text":"","percent":null},"wto":{"text":"","percent":null},"chinaRcep":{"text":"3.4%","percent":3.4}},{"hs6":"711320","statisticalCode":"000","code":"711320000","description":"Of base metal clad with precious metal","general":{"text":"6.6%","percent":6.6},"temporary":{"text":"","percent":null},"wto":{"text":"5.4%","percent":5.4},"chinaRcep":{"text":"2.5%","percent":2.5}},{"hs6":"711320","statisticalCode":"","code":"711320","description":"Articles of goldsmiths' or silversmiths' wares and parts thereof, of precious metal or of metal clad with precious metal","general":{"text":"6.6%","percent":6.6},"temporary":{"text":"","percent":null},"wto":{"text":"5.4%","percent":5.4},"chinaRcep":{"text":"2.5%","percent":2.5}},{"hs6":"711320","statisticalCode":"","code":"711320","description":"Of precious metal whether or not plated or clad with precious metal :","general":{"text":"6.6%","percent":6.6},"temporary":{"text":"","percent":null},"wto":{"text":"5.4%","percent":5.4},"chinaRcep":{"text":"2.5%","percent":2.5}},{"hs6":"711411","statisticalCode":"000","code":"711411000","description":"Of silver, whether or not plated or clad with other precious metal","general":{"text":"6.6%","percent":6.6},"temporary":{"text":"","percent":null},"wto":{"text":"5.4%","percent":5.4},"chinaRcep":{"text":"Free","percent":0}},{"hs6":"711419","statisticalCode":"000","code":"711419000","description":"Of other precious metal, whether or not plated or clad with precious metal","general":{"text":"3.3%","percent":3.3},"temporary":{"text":"","percent":null},"wto":{"text":"3.3%","percent":3.3},"chinaRcep":{"text":"Free","percent":0}},{"hs6":"711420","statisticalCode":"000","code":"711420000","description":"Of base metal clad with precious metal","general":{"text":"3.3%","percent":3.3},"temporary":{"text":"","percent":null},"wto":{"text":"3.3%","percent":3.3},"chinaRcep":{"text":"Free","percent":0}},{"hs6":"711420","statisticalCode":"","code":"711420","description":"Other articles of precious metal or of metal clad with precious metal","general":{"text":"3.3%","percent":3.3},"temporary":{"text":"","percent":null},"wto":{"text":"3.3%","percent":3.3},"chinaRcep":{"text":"Free","percent":0}},{"hs6":"711510","statisticalCode":"000","code":"711510000","description":"Catalysts in the form of wire cloth or grill, of platinum","general":{"text":"Free","percent":0},"temporary":{"text":"","percent":null},"wto":{"text":"Free","percent":0},"chinaRcep":{"text":"Free","percent":0}},{"hs6":"711590","statisticalCode":"000","code":"711590000","description":"Other","general":{"text":"Free","percent":0},"temporary":{"text":"","percent":null},"wto":{"text":"Free","percent":0},"chinaRcep":{"text":"Free","percent":0}},{"hs6":"711590","statisticalCode":"","code":"711590","description":"Articles of natural or cultured pearls, precious or semi-precious stones (natural, synthetic or reconstructed)","general":{"text":"Free","percent":0},"temporary":{"text":"","percent":null},"wto":{"text":"Free","percent":0},"chinaRcep":{"text":"Free","percent":0}},{"hs6":"711610","statisticalCode":"000","code":"711610000","description":"Of natural or cultured pearls","general":{"text":"6.2%","percent":6.2},"temporary":{"text":"","percent":null},"wto":{"text":"5.2%","percent":5.2},"chinaRcep":{"text":"2.4%","percent":2.4}},{"hs6":"711620","statisticalCode":"","code":"711620","description":"Of precious or semi-precious stones (natural, synthetic or reconstructed)","general":{"text":"","percent":null},"temporary":{"text":"","percent":null},"wto":{"text":"","percent":null},"chinaRcep":{"text":"","percent":null}},{"hs6":"711620","statisticalCode":"100","code":"711620100","description":"1 For laboratory or industrial purposes","general":{"text":"3%","percent":3},"temporary":{"text":"","percent":null},"wto":{"text":"2.5%","percent":2.5},"chinaRcep":{"text":"Free","percent":0}},{"hs6":"711620","statisticalCode":"","code":"711620","description":"2 Other","general":{"text":"6.2%","percent":6.2},"temporary":{"text":"","percent":null},"wto":{"text":"5.2%","percent":5.2},"chinaRcep":{"text":"","percent":null}},{"hs6":"711620","statisticalCode":"210","code":"711620210","description":"- Jewellery and parts thereof","general":{"text":"","percent":null},"temporary":{"text":"","percent":null},"wto":{"text":"","percent":null},"chinaRcep":{"text":"2.4%","percent":2.4}},{"hs6":"711620","statisticalCode":"290","code":"711620290","description":"- Other","general":{"text":"","percent":null},"temporary":{"text":"","percent":null},"wto":{"text":"","percent":null},"chinaRcep":{"text":"Free","percent":0}},{"hs6":"711620","statisticalCode":"","code":"711620","description":"Imitation jewellery","general":{"text":"","percent":null},"temporary":{"text":"","percent":null},"wto":{"text":"","percent":null},"chinaRcep":{"text":"","percent":null}},{"hs6":"711620","statisticalCode":"","code":"711620","description":"Of base metal, whether or not plated with precious metal :","general":{"text":"","percent":null},"temporary":{"text":"","percent":null},"wto":{"text":"","percent":null},"chinaRcep":{"text":"","percent":null}},{"hs6":"711711","statisticalCode":"","code":"711711","description":"Cuff-links and studs","general":{"text":"","percent":null},"temporary":{"text":"","percent":null},"wto":{"text":"","percent":null},"chinaRcep":{"text":"","percent":null}},{"hs6":"711711","statisticalCode":"010","code":"711711010","description":"1 Made of, or combined with metal plated with precious metal, coral, elephants' tusks or Bekko","general":{"text":"6.6%","percent":6.6},"temporary":{"text":"","percent":null},"wto":{"text":"5.4%","percent":5.4},"chinaRcep":{"text":"Free","percent":0}},{"hs6":"711711","statisticalCode":"020","code":"711711020","description":"2 Other","general":{"text":"6.4%","percent":6.4},"temporary":{"text":"","percent":null},"wto":{"text":"5.3%","percent":5.3},"chinaRcep":{"text":"Free","percent":0}},{"hs6":"711719","statisticalCode":"","code":"711719","description":"Other","general":{"text":"5.6%","percent":5.6},"temporary":{"text":"","percent":null},"wto":{"text":"3.7%","percent":3.7},"chinaRcep":{"text":"","percent":null}},{"hs6":"711719","statisticalCode":"010","code":"711719010","description":"- Plated with precious metal","general":{"text":"5.6%","percent":5.6},"temporary":{"text":"","percent":null},"wto":{"text":"3.7%","percent":3.7},"chinaRcep":{"text":"1.7%","percent":1.7}},{"hs6":"711719","statisticalCode":"090","code":"711719090","description":"- Other","general":{"text":"5.6%","percent":5.6},"temporary":{"text":"","percent":null},"wto":{"text":"3.7%","percent":3.7},"chinaRcep":{"text":"2.3%","percent":2.3}},{"hs6":"711790","statisticalCode":"","code":"711790","description":"Other","general":{"text":"","percent":null},"temporary":{"text":"","percent":null},"wto":{"text":"","percent":null},"chinaRcep":{"text":"","percent":null}},{"hs6":"711790","statisticalCode":"010","code":"711790010","description":"1 Of at least two materials (for example, wood and glass, bone and amber, mother-of-pearl and plastics), no account being taken of materials (for example, necklace strings) used only for assembly, not plated with precious metal","general":{"text":"12.5%","percent":12.5},"temporary":{"text":"","percent":null},"wto":{"text":"10%","percent":10},"chinaRcep":{"text":"4.5%","percent":4.5}},{"hs6":"711790","statisticalCode":"","code":"711790","description":"2 Other","general":{"text":"","percent":null},"temporary":{"text":"","percent":null},"wto":{"text":"","percent":null},"chinaRcep":{"text":"","percent":null}},{"hs6":"711790","statisticalCode":"021","code":"711790021","description":"(1)Of wood","general":{"text":"3.2%","percent":3.2},"temporary":{"text":"","percent":null},"wto":{"text":"2.7%","percent":2.7},"chinaRcep":{"text":"Free","percent":0}},{"hs6":"711790","statisticalCode":"022","code":"711790022","description":"(2)Of ivory, of bone, of tortoise-shell, of horn, of antlers, of coral, of mother-of-pearl or of other animal carving material","general":{"text":"4.1%","percent":4.1},"temporary":{"text":"","percent":null},"wto":{"text":"3.4%","percent":3.4},"chinaRcep":{"text":"Free","percent":0}},{"hs6":"711790","statisticalCode":"","code":"711790","description":"(3)Other","general":{"text":"5.5%","percent":5.5},"temporary":{"text":"","percent":null},"wto":{"text":"5%","percent":5},"chinaRcep":{"text":"","percent":null}},{"hs6":"711790","statisticalCode":"023","code":"711790023","description":"- Of plastics","general":{"text":"","percent":null},"temporary":{"text":"","percent":null},"wto":{"text":"","percent":null},"chinaRcep":{"text":"2.3%","percent":2.3}},{"hs6":"711790","statisticalCode":"","code":"711790","description":"- Other","general":{"text":"","percent":null},"temporary":{"text":"","percent":null},"wto":{"text":"","percent":null},"chinaRcep":{"text":"","percent":null}},{"hs6":"711790","statisticalCode":"024","code":"711790024","description":"-- Plated with precious metal","general":{"text":"","percent":null},"temporary":{"text":"","percent":null},"wto":{"text":"","percent":null},"chinaRcep":{"text":"2.3%","percent":2.3}},{"hs6":"711790","statisticalCode":"029","code":"711790029","description":"-- Other","general":{"text":"","percent":null},"temporary":{"text":"","percent":null},"wto":{"text":"","percent":null},"chinaRcep":{"text":"Free","percent":0}},{"hs6":"711790","statisticalCode":"","code":"711790","description":"Coin","general":{"text":"","percent":null},"temporary":{"text":"","percent":null},"wto":{"text":"","percent":null},"chinaRcep":{"text":"","percent":null}},{"hs6":"711810","statisticalCode":"000","code":"711810000","description":"Coin (other than gold coin), not being legal tender","general":{"text":"Free","percent":0},"temporary":{"text":"","percent":null},"wto":{"text":"Free","percent":0},"chinaRcep":{"text":"Free","percent":0}},{"hs6":"711890","statisticalCode":"","code":"711890","description":"Other","general":{"text":"Free","percent":0},"temporary":{"text":"","percent":null},"wto":{"text":"Free","percent":0},"chinaRcep":{"text":"","percent":null}},{"hs6":"711890","statisticalCode":"010","code":"711890010","description":"- Gold coin","general":{"text":"Free","percent":0},"temporary":{"text":"","percent":null},"wto":{"text":"Free","percent":0},"chinaRcep":{"text":"Free","percent":0}},{"hs6":"711890","statisticalCode":"090","code":"711890090","description":"- Other","general":{"text":"Free","percent":0},"temporary":{"text":"","percent":null},"wto":{"text":"Free","percent":0},"chinaRcep":{"text":"Free","percent":0}}]